tasxnat/__init__.py
tasxnat/objects.py
tasxnat/protocols.py
tasxnat/utilities.py
tasxnat-0.0.8.dist-info/LICENSE.txt
tasxnat-0.0.8.dist-info/METADATA
tasxnat-0.0.8.dist-info/WHEEL
tasxnat-0.0.8.dist-info/top_level.txt
tasxnat-0.0.8.dist-info/RECORD
